{
  "timestamp": "20260618-151611",
  "rule_inventory": {
    "path": "data/enterprise_docs/rule_inventory.json",
    "rule_count": 27,
    "by_class": {
      "reusable_generic_rule": 13,
      "pattern_specific_rule": 3,
      "pilot_only_rule": 7,
      "coverage_or_abstain_rule": 2,
      "synthesis_blocker_rule": 2
    }
  },
  "reusability_audit": {
    "path": "reports/enterprise_docs_reusability_audit.json",
    "reusable_system_coverage": 0.4815,
    "pilot_only_dependency": 0.2593,
    "productize_candidates": [
      "ED-PARSE-001",
      "ED-PARSE-002",
      "ED-INGEST-001",
      "ED-RETR-001",
      "ED-RETR-002",
      "ED-RETR-003",
      "ED-RETR-005",
      "ED-EXT-001",
      "ED-EXT-002",
      "ED-EXT-006",
      "ED-EXT-007",
      "ED-AGG-001",
      "ED-AGG-002",
      "ED-AGG-004",
      "ED-AGG-005",
      "ED-DIAG-001",
      "ED-DIAG-002",
      "ED-DIAG-003",
      "ED-QUAL-001"
    ],
    "abstraction_backlog": [
      "ED-ROUTE-001",
      "ED-EXT-004",
      "ED-EXT-005",
      "ED-AGG-003"
    ]
  },
  "demo_readiness": {
    "total": 35,
    "readiness_counts": {
      "extraction_ready": 8,
      "retrieval_ready": 14,
      "not_ready_for_synthesis": 5,
      "single_source_sufficient": 6,
      "multi_source_sufficient": 1,
      "honest_abstain": 1
    },
    "readiness_rates": {
      "extraction_ready": 0.2286,
      "retrieval_ready": 0.4,
      "not_ready_for_synthesis": 0.1429,
      "single_source_sufficient": 0.1714,
      "multi_source_sufficient": 0.0286,
      "honest_abstain": 0.0286
    },
    "by_kind": {
      "quantitative": {
        "extraction_ready": 8,
        "retrieval_ready": 14,
        "single_source_sufficient": 6,
        "multi_source_sufficient": 1,
        "honest_abstain": 1
      },
      "qualitative": {
        "not_ready_for_synthesis": 5
      }
    },
    "by_answer_mode": {
      "single_document_answer": {
        "extraction_ready": 8,
        "retrieval_ready": 12
      },
      "cross_document_answer": {
        "not_ready_for_synthesis": 5,
        "single_source_sufficient": 6,
        "retrieval_ready": 2,
        "multi_source_sufficient": 1,
        "honest_abstain": 1
      }
    },
    "quantitative_count": 30,
    "qualitative_count": 5,
    "synthesis_gate_allowed_count": 7,
    "synthesis_gate_allowed_rate_quant": 0.2333
  },
  "demo_readiness_rows": [
    {
      "item_id": "QUANT-0001",
      "kind": "quantitative",
      "answer_mode": "single_document_answer",
      "readiness_state": "extraction_ready",
      "readiness_reason": "matched_row:총 임직원",
      "retrieval_ok": true,
      "extraction_success": true,
      "aggregation_status": null,
      "sufficiency_status": null,
      "resolved_value": "약 180000",
      "fail_stage": "ready",
      "open_synthesis_allowed": false
    },
    {
      "item_id": "QUANT-0006",
      "kind": "quantitative",
      "answer_mode": "single_document_answer",
      "readiness_state": "extraction_ready",
      "readiness_reason": "matched_row:정규직 직원 비율",
      "retrieval_ok": true,
      "extraction_success": true,
      "aggregation_status": null,
      "sufficiency_status": null,
      "resolved_value": "98.4",
      "fail_stage": "ready",
      "open_synthesis_allowed": false
    },
    {
      "item_id": "QUANT-0013",
      "kind": "quantitative",
      "answer_mode": "single_document_answer",
      "readiness_state": "retrieval_ready",
      "readiness_reason": "ready",
      "retrieval_ok": true,
      "extraction_success": false,
      "aggregation_status": null,
      "sufficiency_status": null,
      "resolved_value": null,
      "fail_stage": "ready",
      "open_synthesis_allowed": false
    },
    {
      "item_id": "QUANT-0019",
      "kind": "quantitative",
      "answer_mode": "single_document_answer",
      "readiness_state": "retrieval_ready",
      "readiness_reason": "ready",
      "retrieval_ok": true,
      "extraction_success": false,
      "aggregation_status": null,
      "sufficiency_status": null,
      "resolved_value": null,
      "fail_stage": "ready",
      "open_synthesis_allowed": false
    },
    {
      "item_id": "QUANT-0028",
      "kind": "quantitative",
      "answer_mode": "single_document_answer",
      "readiness_state": "extraction_ready",
      "readiness_reason": "matched_row:자발적 이직률",
      "retrieval_ok": true,
      "extraction_success": true,
      "aggregation_status": null,
      "sufficiency_status": null,
      "resolved_value": "4.2",
      "fail_stage": "ready",
      "open_synthesis_allowed": false
    },
    {
      "item_id": "QUANT-0146",
      "kind": "quantitative",
      "answer_mode": "single_document_answer",
      "readiness_state": "retrieval_ready",
      "readiness_reason": "retrieval_sufficient_for_next_stage",
      "retrieval_ok": true,
      "extraction_success": false,
      "aggregation_status": null,
      "sufficiency_status": null,
      "resolved_value": null,
      "fail_stage": "ready",
      "open_synthesis_allowed": false
    },
    {
      "item_id": "QUANT-0147",
      "kind": "quantitative",
      "answer_mode": "single_document_answer",
      "readiness_state": "retrieval_ready",
      "readiness_reason": "ready",
      "retrieval_ok": true,
      "extraction_success": false,
      "aggregation_status": null,
      "sufficiency_status": null,
      "resolved_value": null,
      "fail_stage": "ready",
      "open_synthesis_allowed": false
    },
    {
      "item_id": "QUANT-0151",
      "kind": "quantitative",
      "answer_mode": "single_document_answer",
      "readiness_state": "extraction_ready",
      "readiness_reason": "matched_row:총 에너지 소비량",
      "retrieval_ok": true,
      "extraction_success": true,
      "aggregation_status": null,
      "sufficiency_status": null,
      "resolved_value": "19278.0",
      "fail_stage": "ready",
      "open_synthesis_allowed": false
    },
    {
      "item_id": "QUANT-0200",
      "kind": "quantitative",
      "answer_mode": "single_document_answer",
      "readiness_state": "extraction_ready",
      "readiness_reason": "matched_row:폐수 배출량, CDP total water discharges",
      "retrieval_ok": true,
      "extraction_success": true,
      "aggregation_status": null,
      "sufficiency_status": null,
      "resolved_value": "5069000",
      "fail_stage": "ready",
      "open_synthesis_allowed": false
    },
    {
      "item_id": "QUANT-0215",
      "kind": "quantitative",
      "answer_mode": "single_document_answer",
      "readiness_state": "retrieval_ready",
      "readiness_reason": "coverage=0.0,doc_hit=0.0",
      "retrieval_ok": true,
      "extraction_success": false,
      "aggregation_status": null,
      "sufficiency_status": null,
      "resolved_value": null,
      "fail_stage": "retrieval_gap",
      "open_synthesis_allowed": false
    },
    {
      "item_id": "QUANT-0219",
      "kind": "quantitative",
      "answer_mode": "single_document_answer",
      "readiness_state": "retrieval_ready",
      "readiness_reason": "ready",
      "retrieval_ok": true,
      "extraction_success": false,
      "aggregation_status": null,
      "sufficiency_status": null,
      "resolved_value": null,
      "fail_stage": "ready",
      "open_synthesis_allowed": false
    },
    {
      "item_id": "QUANT-0224",
      "kind": "quantitative",
      "answer_mode": "single_document_answer",
      "readiness_state": "retrieval_ready",
      "readiness_reason": "ready",
      "retrieval_ok": true,
      "extraction_success": false,
      "aggregation_status": null,
      "sufficiency_status": null,
      "resolved_value": null,
      "fail_stage": "ready",
      "open_synthesis_allowed": false
    },
    {
      "item_id": "QUANT-0207",
      "kind": "quantitative",
      "answer_mode": "single_document_answer",
      "readiness_state": "retrieval_ready",
      "readiness_reason": "ready",
      "retrieval_ok": true,
      "extraction_success": false,
      "aggregation_status": null,
      "sufficiency_status": null,
      "resolved_value": null,
      "fail_stage": "ready",
      "open_synthesis_allowed": false
    },
    {
      "item_id": "QUANT-0083",
      "kind": "quantitative",
      "answer_mode": "single_document_answer",
      "readiness_state": "extraction_ready",
      "readiness_reason": "matched_row:근로자 1인당 연간 근로시간, calculated proxy",
      "retrieval_ok": true,
      "extraction_success": true,
      "aggregation_status": null,
      "sufficiency_status": null,
      "resolved_value": "1992.6",
      "fail_stage": "ready",
      "open_synthesis_allowed": false
    },
    {
      "item_id": "QUANT-0086",
      "kind": "quantitative",
      "answer_mode": "single_document_answer",
      "readiness_state": "retrieval_ready",
      "readiness_reason": "coverage=0.0,doc_hit=0.0",
      "retrieval_ok": true,
      "extraction_success": false,
      "aggregation_status": null,
      "sufficiency_status": null,
      "resolved_value": null,
      "fail_stage": "retrieval_gap",
      "open_synthesis_allowed": false
    },
    {
      "item_id": "QUANT-0126",
      "kind": "quantitative",
      "answer_mode": "single_document_answer",
      "readiness_state": "extraction_ready",
      "readiness_reason": "matched_row:Total corporate giving",
      "retrieval_ok": true,
      "extraction_success": true,
      "aggregation_status": null,
      "sufficiency_status": null,
      "resolved_value": "53.6",
      "fail_stage": "ready",
      "open_synthesis_allowed": false
    },
    {
      "item_id": "QUANT-0144",
      "kind": "quantitative",
      "answer_mode": "single_document_answer",
      "readiness_state": "retrieval_ready",
      "readiness_reason": "ready",
      "retrieval_ok": true,
      "extraction_success": false,
      "aggregation_status": null,
      "sufficiency_status": null,
      "resolved_value": null,
      "fail_stage": "ready",
      "open_synthesis_allowed": false
    },
    {
      "item_id": "QUANT-0017",
      "kind": "quantitative",
      "answer_mode": "single_document_answer",
      "readiness_state": "retrieval_ready",
      "readiness_reason": "retrieval_sufficient_for_next_stage",
      "retrieval_ok": true,
      "extraction_success": false,
      "aggregation_status": null,
      "sufficiency_status": null,
      "resolved_value": null,
      "fail_stage": "ready",
      "open_synthesis_allowed": false
    },
    {
      "item_id": "QUANT-0031",
      "kind": "quantitative",
      "answer_mode": "single_document_answer",
      "readiness_state": "extraction_ready",
      "readiness_reason": "matched_row:자발적 이직률",
      "retrieval_ok": true,
      "extraction_success": true,
      "aggregation_status": null,
      "sufficiency_status": null,
      "resolved_value": "4.2",
      "fail_stage": "ready",
      "open_synthesis_allowed": false
    },
    {
      "item_id": "QUANT-0220",
      "kind": "quantitative",
      "answer_mode": "single_document_answer",
      "readiness_state": "retrieval_ready",
      "readiness_reason": "ready",
      "retrieval_ok": true,
      "extraction_success": false,
      "aggregation_status": null,
      "sufficiency_status": null,
      "resolved_value": null,
      "fail_stage": "ready",
      "open_synthesis_allowed": false
    },
    {
      "item_id": "QUAL-0001",
      "kind": "qualitative",
      "answer_mode": "cross_document_answer",
      "readiness_state": "not_ready_for_synthesis",
      "readiness_reason": "qualitative_requires_synthesis_gate",
      "retrieval_ok": true,
      "extraction_success": false,
      "aggregation_status": "failed",
      "sufficiency_status": "failed",
      "resolved_value": null,
      "fail_stage": "synthesis_gap",
      "open_synthesis_allowed": false
    },
    {
      "item_id": "QUAL-0002",
      "kind": "qualitative",
      "answer_mode": "cross_document_answer",
      "readiness_state": "not_ready_for_synthesis",
      "readiness_reason": "qualitative_requires_synthesis_gate",
      "retrieval_ok": true,
      "extraction_success": false,
      "aggregation_status": "failed",
      "sufficiency_status": "failed",
      "resolved_value": null,
      "fail_stage": "ready",
      "open_synthesis_allowed": false
    },
    {
      "item_id": "QUAL-0005",
      "kind": "qualitative",
      "answer_mode": "cross_document_answer",
      "readiness_state": "not_ready_for_synthesis",
      "readiness_reason": "qualitative_requires_synthesis_gate",
      "retrieval_ok": true,
      "extraction_success": false,
      "aggregation_status": "failed",
      "sufficiency_status": "failed",
      "resolved_value": null,
      "fail_stage": "ready",
      "open_synthesis_allowed": false
    },
    {
      "item_id": "QUAL-0008",
      "kind": "qualitative",
      "answer_mode": "cross_document_answer",
      "readiness_state": "not_ready_for_synthesis",
      "readiness_reason": "qualitative_requires_synthesis_gate",
      "retrieval_ok": true,
      "extraction_success": false,
      "aggregation_status": "failed",
      "sufficiency_status": "failed",
      "resolved_value": null,
      "fail_stage": "ready",
      "open_synthesis_allowed": false
    },
    {
      "item_id": "QUAL-0020",
      "kind": "qualitative",
      "answer_mode": "cross_document_answer",
      "readiness_state": "not_ready_for_synthesis",
      "readiness_reason": "qualitative_requires_synthesis_gate",
      "retrieval_ok": true,
      "extraction_success": false,
      "aggregation_status": "failed",
      "sufficiency_status": "failed",
      "resolved_value": null,
      "fail_stage": "synthesis_gap",
      "open_synthesis_allowed": false
    },
    {
      "item_id": "QUANT-0042",
      "kind": "quantitative",
      "answer_mode": "cross_document_answer",
      "readiness_state": "single_source_sufficient",
      "readiness_reason": "single_authoritative_source_metric_absent_elsewhere",
      "retrieval_ok": true,
      "extraction_success": true,
      "aggregation_status": "success",
      "sufficiency_status": "resolved_single_source_sufficient",
      "resolved_value": "25.3",
      "fail_stage": "ready",
      "open_synthesis_allowed": true
    },
    {
      "item_id": "QUANT-0044",
      "kind": "quantitative",
      "answer_mode": "cross_document_answer",
      "readiness_state": "retrieval_ready",
      "readiness_reason": "retrieval_sufficient_for_next_stage",
      "retrieval_ok": true,
      "extraction_success": false,
      "aggregation_status": "failed",
      "sufficiency_status": "failed",
      "resolved_value": null,
      "fail_stage": "ready",
      "open_synthesis_allowed": false
    },
    {
      "item_id": "QUANT-0133",
      "kind": "quantitative",
      "answer_mode": "cross_document_answer",
      "readiness_state": "single_source_sufficient",
      "readiness_reason": "single_authoritative_source_metric_absent_elsewhere",
      "retrieval_ok": true,
      "extraction_success": false,
      "aggregation_status": "success",
      "sufficiency_status": "resolved_single_source_sufficient",
      "resolved_value": "20.8",
      "fail_stage": "ready",
      "open_synthesis_allowed": true
    },
    {
      "item_id": "QUANT-0134",
      "kind": "quantitative",
      "answer_mode": "cross_document_answer",
      "readiness_state": "retrieval_ready",
      "readiness_reason": "retrieval_sufficient_for_next_stage",
      "retrieval_ok": true,
      "extraction_success": false,
      "aggregation_status": "failed",
      "sufficiency_status": "failed",
      "resolved_value": null,
      "fail_stage": "ready",
      "open_synthesis_allowed": false
    },
    {
      "item_id": "QUANT-0208",
      "kind": "quantitative",
      "answer_mode": "cross_document_answer",
      "readiness_state": "single_source_sufficient",
      "readiness_reason": "single_authoritative_source_metric_absent_elsewhere",
      "retrieval_ok": true,
      "extraction_success": true,
      "aggregation_status": "success",
      "sufficiency_status": "resolved_single_source_sufficient",
      "resolved_value": "2,625",
      "fail_stage": "ready",
      "open_synthesis_allowed": true
    },
    {
      "item_id": "QUANT-0210",
      "kind": "quantitative",
      "answer_mode": "cross_document_answer",
      "readiness_state": "single_source_sufficient",
      "readiness_reason": "single_authoritative_source_metric_absent_elsewhere",
      "retrieval_ok": true,
      "extraction_success": true,
      "aggregation_status": "success",
      "sufficiency_status": "resolved_single_source_sufficient",
      "resolved_value": "1.4",
      "fail_stage": "ready",
      "open_synthesis_allowed": true
    },
    {
      "item_id": "QUANT-0209",
      "kind": "quantitative",
      "answer_mode": "cross_document_answer",
      "readiness_state": "single_source_sufficient",
      "readiness_reason": "single_authoritative_source_metric_absent_elsewhere",
      "retrieval_ok": true,
      "extraction_success": true,
      "aggregation_status": "success",
      "sufficiency_status": "resolved_single_source_sufficient",
      "resolved_value": "1,862",
      "fail_stage": "ready",
      "open_synthesis_allowed": true
    },
    {
      "item_id": "QUANT-0213",
      "kind": "quantitative",
      "answer_mode": "cross_document_answer",
      "readiness_state": "single_source_sufficient",
      "readiness_reason": "single_authoritative_source_metric_absent_elsewhere",
      "retrieval_ok": true,
      "extraction_success": true,
      "aggregation_status": "success",
      "sufficiency_status": "resolved_single_source_sufficient",
      "resolved_value": "1,181",
      "fail_stage": "ready",
      "open_synthesis_allowed": true
    },
    {
      "item_id": "QUANT-0155",
      "kind": "quantitative",
      "answer_mode": "cross_document_answer",
      "readiness_state": "multi_source_sufficient",
      "readiness_reason": "resolved",
      "retrieval_ok": true,
      "extraction_success": true,
      "aggregation_status": "success",
      "sufficiency_status": "resolved",
      "resolved_value": "35.0",
      "fail_stage": "ready",
      "open_synthesis_allowed": true
    },
    {
      "item_id": "QUANT-0046",
      "kind": "quantitative",
      "answer_mode": "cross_document_answer",
      "readiness_state": "honest_abstain",
      "readiness_reason": "source_not_disclosed_for_metric",
      "retrieval_ok": true,
      "extraction_success": false,
      "aggregation_status": "failed",
      "sufficiency_status": "failed",
      "resolved_value": null,
      "fail_stage": "ready",
      "open_synthesis_allowed": false
    }
  ],
  "holdout_summary": {
    "probe_count": 8,
    "parser_ok_rate": 1.0,
    "retrieval_feasible_rate": 0.0,
    "extraction_feasible_rate": 0.0,
    "aggregation_feasible_rate": 0.0,
    "reusable_signals": [
      "reusable:ED-PARSE-001",
      "reusable:ED-QUAL-001"
    ],
    "corpus_specific_signals": [
      "corpus_specific:ED-MAP-001_no_logical_mapping",
      "corpus_specific:narrative_only_no_table"
    ],
    "abstraction_signals": [
      "needs_abstraction:ED-EXT-005_narrative_patterns",
      "needs_abstraction:synthesis_gate"
    ]
  },
  "holdout_corpus_note": "Holdout corpus = pilot_hanssem_15_eligible (narrative SR chunks); feasibility only, no gold answer scoring",
  "architecture_decision": {
    "continue_demo_company_dev": true,
    "expand_to_hanssem_musinsa_holdout": false,
    "open_synthesis_yet": false,
    "priority_next": "abstraction_rule_registry",
    "weakest_layer": "retrieval"
  },
  "open_synthesis": false,
  "conclusion": "Lane co 13 reusable rules / 27 total; demo quant synthesis-gate 0.2333; holdout retrieval 0.0; chua mo synthesis; can abstraction truoc full holdout.",
  "answers": {
    "expand_beyond_demo_company": false,
    "open_synthesis": false,
    "weakest_layer": "retrieval",
    "next_system_step": "abstraction_rule_registry"
  }
}